kerfed/client/__init__.py
kerfed/client/engine.py
kerfed/client/models.py
kerfed_client-0.2.2.dist-info/licenses/LICENSE.md
kerfed_client-0.2.2.dist-info/METADATA
kerfed_client-0.2.2.dist-info/WHEEL
kerfed_client-0.2.2.dist-info/top_level.txt
kerfed_client-0.2.2.dist-info/RECORD
