Metadata-Version: 2.4
Name: kerfed.client
Version: 0.2.2
Summary: Library for analyzing CAD geometry.
Author: Kerfed, Inc.
License: The MIT License (MIT)
Project-URL: Homepage, https://github.com/kerfed/client
Keywords: manufacturing
Requires-Python: >=3.7
License-File: LICENSE.md
Requires-Dist: authlib
Requires-Dist: httpx
Dynamic: license-file
